llmskit/__init__.py
llmskit/_retry.py
llmskit/_types.py
llmskit/_utils.py
llmskit/chat.py
llmskit/embedding.py
llmskit/reranker.py
llmskit/clients/__init__.py
llmskit/clients/base.py
llmskit/clients/claude.py
llmskit/clients/openai.py
llmskit-0.0.9.dist-info/licenses/LICENSE
llmskit-0.0.9.dist-info/METADATA
llmskit-0.0.9.dist-info/WHEEL
llmskit-0.0.9.dist-info/top_level.txt
llmskit-0.0.9.dist-info/RECORD
