Metadata-Version: 2.4
Name: llmskit
Version: 0.0.9
Summary: Client and Tools for LLMs
Author-email: hongbo liu <bananabo@foxmail.com>
License: Apache-2.0
Project-URL: Homepage, https://gitee.com/maxbanana
Classifier: Programming Language :: Python :: 3
Classifier: License :: OSI Approved :: Apache Software License
Classifier: Operating System :: OS Independent
Requires-Python: >=3.9
License-File: LICENSE
Requires-Dist: httpx>=0.28.1
Requires-Dist: openai>=2.14.0
Requires-Dist: tenacity>=8.2.3
Requires-Dist: anthropic>=0.75.0
Dynamic: license-file
